scverse/__init__.py
scverse-0.0.1.dist-info/WHEEL
scverse-0.0.1.dist-info/METADATA
scverse-0.0.1.dist-info/RECORD
