Metadata-Version: 2.1
Name: scverse
Version: 0.0.1
Summary: scverse bundle
Home-page: https://github.com/gtca/scverse
Author: Danila Bredikhin
Author-email: danila.bredikhin@embl.de
Requires-Python: >= 3.7
Classifier: Programming Language :: Python :: 3
Classifier: License :: OSI Approved :: BSD License
Classifier: Operating System :: OS Independent
Classifier: Development Status :: 3 - Alpha
Classifier: Topic :: Scientific/Engineering :: Bio-Informatics
Classifier: Intended Audience :: Science/Research
Requires-Dist: anndata
Requires-Dist: scanpy
Requires-Dist: mudata
Requires-Dist: muon
Requires-Dist: pybedtools ; extra == "atac"
Requires-Dist: pysam ; extra == "atac"
Requires-Dist: sphinx >= 4.0 ; extra == "docs"
Requires-Dist: sphinx-rtd-theme ; extra == "docs"
Requires-Dist: readthedocs-sphinx-search ; extra == "docs"
Requires-Dist: nbsphinx ; extra == "docs"
Requires-Dist: sphinx_automodapi ; extra == "docs"
Project-URL: Documentation, https://scverse.org/
Provides-Extra: atac
Provides-Extra: docs
